asgi_cors_middleware/__init__.py
asgi_cors_middleware/middleware.py
asgi_cors_middleware-0.0.2.dist-info/LICENSE
asgi_cors_middleware-0.0.2.dist-info/METADATA
asgi_cors_middleware-0.0.2.dist-info/WHEEL
asgi_cors_middleware-0.0.2.dist-info/top_level.txt
asgi_cors_middleware-0.0.2.dist-info/RECORD
