Metadata-Version: 2.1
Name: asgi-cors-middleware
Version: 0.0.2
Summary: Whitelist urls on ASGI applications allowing for cross origin requests
Home-page: https://github.com/mrkiura/asgi-cors-middleware
Author: Alex Kiura
Author-email: kiuraalex@gmail.com
License: MIT
Classifier: License :: OSI Approved :: MIT License
Classifier: Programming Language :: Python :: 3
Classifier: Programming Language :: Python :: 3.7
License-File: LICENSE
Requires-Dist: starlette
Requires-Dist: asgiref (>=3.5.0)
